xrdownloader/__init__.py
xrdownloader/banner.py
xrdownloader/convert.py
xrdownloader/resume.py
xrdownloader/xrUrllib3Conf.py
xrdownloader/xrmain.py
xrdownloader-1.0.6.dist-info/METADATA
xrdownloader-1.0.6.dist-info/WHEEL
xrdownloader-1.0.6.dist-info/top_level.txt
xrdownloader-1.0.6.dist-info/RECORD
