Metadata-Version: 2.1
Name: xrdownloader
Version: 1.0.6
Summary: XploitsR | XRDownloader is a module for faster downloading of files.
Home-page: https://github.com/XploitsR/XRDownloader
Author: XploitsR Author (solomon narh)
Author-email: solomonnarh97062@gmail.com
Maintainer: XploitsR Authors
Maintainer-email: xploitsr@gmail.com
License: MIT
Keywords: xrdownloader fast-downloader xploitsr-author1 xploitsr
Platform: any
Classifier: License :: OSI Approved :: MIT License
Classifier: Operating System :: OS Independent
Classifier: Programming Language :: Python
Classifier: Programming Language :: Python :: 2
Classifier: Programming Language :: Python :: 2.6
Classifier: Programming Language :: Python :: 2.7
Classifier: Programming Language :: Python :: 3
Classifier: Programming Language :: Python :: 3.2
Classifier: Programming Language :: Python :: 3.3
Classifier: Programming Language :: Python :: 3.4
Classifier: Programming Language :: Python :: 3.5
Classifier: Programming Language :: Python :: 3.6
Classifier: Programming Language :: Python :: 3.7
Requires-Python: >=2.6, !=3.0.*, !=3.1.*
Requires-Dist: urllib3
Requires-Dist: certifi
Requires-Dist: pyfiglet
Requires-Dist: tqdm
